ScrapeTweets/__init__.py
ScrapeTweets-1.0.0.dist-info/LICENSE
ScrapeTweets-1.0.0.dist-info/METADATA
ScrapeTweets-1.0.0.dist-info/WHEEL
ScrapeTweets-1.0.0.dist-info/top_level.txt
ScrapeTweets-1.0.0.dist-info/RECORD
