Metadata-Version: 2.1
Name: ScrapeTweets
Version: 1.0.0
Summary: ScrapeTweets is a Python package that scrapes all the tweets from the Twitter API by using Hashtags. This data can be used for various purposes like Education, Research, News, etc.
Home-page: https://github.com/ManasweeA/ScrapeTweets-PyPi
Author: Manaswee Adwant
Author-email: manaswee25445@gmail.com
License: UNKNOWN
Platform: UNKNOWN
Classifier: Programming Language :: Python :: 3
Classifier: License :: OSI Approved :: MIT License
Classifier: Operating System :: OS Independent
Requires-Python: >=3.0
